mander/__init__.py
mander/districts.py
mander/metrics.py
mander/minBoundingCircle.py
mander/utils.py
mander-0.3.dist-info/DESCRIPTION.rst
mander-0.3.dist-info/METADATA
mander-0.3.dist-info/RECORD
mander-0.3.dist-info/WHEEL
mander-0.3.dist-info/metadata.json
mander-0.3.dist-info/pbr.json
mander-0.3.dist-info/top_level.txt
test/__init__.py
test/metrics.py
