Metadata-Version: 2.0
Name: mander
Version: 0.3
Summary: Python package to calculate compactness metrics for district shapes.
Home-page: http://github.com/gerrymandr/python-mander
Author: Geometry of Redistricting Workshop
Author-email: gerrymandr@gmail.com
License: MIT
Platform: UNKNOWN
Requires-Dist: geopandas
